EdaFirstPhase/eda.py
detect_outliers-0.11.dist-info/METADATA
detect_outliers-0.11.dist-info/WHEEL
detect_outliers-0.11.dist-info/top_level.txt
detect_outliers-0.11.dist-info/RECORD
