Metadata-Version: 2.1
Name: detect-outliers
Version: 0.11
Summary: Complete EDA report
Home-page: UNKNOWN
Author: UNKNOWN
Author-email: UNKNOWN
License: UNKNOWN
Platform: UNKNOWN
